[
  {"index":"1","title":"React 使用指南","desc":"Create React App is a new officially supported way to create single-page React applications. It offers a modern build setup with no configuration. It requires Node 4 or higher.

Note that it has some limitations and is only useful for single-page applications. If you need more flexibility, or if you want to integrate React into an existing project, consider other options below.","url":"a"},
  {"index":"2","title":"武林秘籍第二章","desc":"你值得拥有！你值得拥有！你值得拥有！你值得拥有！你值得拥有！你值得拥有！你值得拥有！你值得拥有！你值得拥有！","url":"b"},
  {"index":"3","title":"武林秘籍第三章","desc":"你值得拥有！你值得拥有！你值得拥有！你值得拥有！你值得拥有！你值得拥有！你值得拥有！你值得拥有！你值得拥有！","url":"c"},
  {"index":"4","title":"武林秘籍第四章","desc":"你值得拥有！你值得拥有！你值得拥有！你值得拥有！你值得拥有！你值得拥有！你值得拥有！你值得拥有！你值得拥有！","url":"d"},
  {"index":"5","title":"武林秘籍第五章","desc":"你值得拥有！你值得拥有！你值得拥有！你值得拥有！你值得拥有！你值得拥有！你值得拥有！你值得拥有！你值得拥有！","url":"e"}
]
